{"components_dom_overview.md":"LSeNNn_O","components_dom_watermark.md":"CowabOr6","components_react_overview.md":"4mU41x6d","components_react_watermark.md":"DFP8u3L5","components_vue_overview.md":"BipnkTV8","components_vue_watermark.md":"BppdvFHl","guide_getting-started.md":"D9pQjmE9","guide_what-is-this.md":"BRe3NyOF","index.md":"Dz87Ah5g","zh_components_dom_overview.md":"DPD4S5ER","zh_components_dom_watermark.md":"DL89rGPL","zh_components_react_overview.md":"CqtYQRol","zh_components_react_watermark.md":"CTgnjVRx","zh_components_vue_overview.md":"B6cz13pk","zh_components_vue_watermark.md":"CkWgRh1f","zh_guide_getting-started.md":"DLqBPytU","zh_guide_what-is-this.md":"CzUc_p0r","zh_index.md":"eyZRm4XG"}
