{"components_vue_overview.md":"BtTfKnz7","zh_index.md":"Q9zjiuL0","guide_what-is-this.md":"C2N1La7W","components_vue_watermark.md":"DKOGMTHb","guide_getting-started.md":"Cyx6Kp1A","zh_guide_what-is-this.md":"jDwwycBy","zh_components_vue_watermark.md":"BzHPM4ue","components_react_overview.md":"B8YhvmGR","components_react_watermark.md":"CoIqtwry","components_dom_watermark.md":"9w9UlMU1","zh_components_dom_overview.md":"BjVw7LGS","zh_guide_getting-started.md":"C98ErEsr","zh_components_react_overview.md":"fgeYaLhq","zh_components_react_watermark.md":"BAsB3mN5","zh_components_vue_overview.md":"CqLZOYA6","zh_components_dom_watermark.md":"jpacgHvh","index.md":"rYvLWgMA","components_dom_overview.md":"DvndRPqw"}
